filelocker/__init__.py
filelocker/__main__.py
filelocker/core.py
filelocker/lang.py
filelocker-0.1.1.dist-info/METADATA
filelocker-0.1.1.dist-info/WHEEL
filelocker-0.1.1.dist-info/entry_points.txt
filelocker-0.1.1.dist-info/top_level.txt
filelocker-0.1.1.dist-info/RECORD
